txfake/__init__.py
txfake/fake_connection.py
txfake-0.1.1.dist-info/DESCRIPTION.rst
txfake-0.1.1.dist-info/METADATA
txfake-0.1.1.dist-info/metadata.json
txfake-0.1.1.dist-info/RECORD
txfake-0.1.1.dist-info/top_level.txt
txfake-0.1.1.dist-info/WHEEL
