Metadata-Version: 2.0
Name: txfake
Version: 0.1.1
Summary: TODO
Home-page: https://github.com/jerith/txfake
Author: Jeremy Thurgood
Author-email: firxen@gmail.com
License: MIT
Platform: UNKNOWN
Requires-Dist: Twisted (>=13.2.0)
